wagtail_headless_preview/__init__.py
wagtail_headless_preview/apps.py
wagtail_headless_preview/deprecation.py
wagtail_headless_preview/models.py
wagtail_headless_preview/settings.py
wagtail_headless_preview/signals.py
wagtail_headless_preview/migrations/0001_initial.py
wagtail_headless_preview/migrations/__init__.py
wagtail_headless_preview/templates/wagtail_headless_preview/preview.html
wagtail_headless_preview-0.8.0.dist-info/LICENSE
wagtail_headless_preview-0.8.0.dist-info/WHEEL
wagtail_headless_preview-0.8.0.dist-info/METADATA
wagtail_headless_preview-0.8.0.dist-info/RECORD
