Metadata-Version: 2.1
Name: wagtail-headless-preview
Version: 0.8.0
Summary: Enhance Wagtail previews in headless setups.
Keywords: Wagtail,Django,headless
Author-email: Dan Braghis <dan.braghis@torchbox.com>
Requires-Python: >=3.8
Classifier: Development Status :: 4 - Beta
Classifier: Environment :: Web Environment
Classifier: Intended Audience :: Developers
Classifier: Operating System :: OS Independent
Classifier: License :: OSI Approved :: BSD License
Classifier: Programming Language :: Python
Classifier: Programming Language :: Python :: 3
Classifier: Programming Language :: Python :: 3.8
Classifier: Programming Language :: Python :: 3.9
Classifier: Programming Language :: Python :: 3.10
Classifier: Programming Language :: Python :: 3.11
Classifier: Programming Language :: Python :: 3.12
Classifier: Framework :: Django
Classifier: Framework :: Django :: 3.2
Classifier: Framework :: Django :: 4.2
Classifier: Framework :: Django :: 5.0
Classifier: Framework :: Wagtail
Classifier: Framework :: Wagtail :: 4
Classifier: Framework :: Wagtail :: 5
Classifier: Framework :: Wagtail :: 6
Classifier: Topic :: Internet :: WWW/HTTP
Classifier: Topic :: Internet :: WWW/HTTP :: Dynamic Content
Requires-Dist: Wagtail>=4.1
Requires-Dist: django-cors-headers ; extra == "testing"
Requires-Dist: tox>=4 ; extra == "testing"
Requires-Dist: coverage[toml]>=7.0,<8.0 ; extra == "testing"
Project-URL: Changelog, https://github.com/torchbox/wagtail-headless-preview/blob/main/CHANGELOG.md
Project-URL: Issues, https://github.com/torchbox/wagtail-headless-preview/issues
Project-URL: Repository, https://github.com/torchbox/wagtail-headless-preview
Provides-Extra: testing
